pinax/__init__.py
pinax/messages/__init__.py
pinax/messages/admin.py
pinax/messages/apps.py
pinax/messages/conf.py
pinax/messages/context_processors.py
pinax/messages/forms.py
pinax/messages/hooks.py
pinax/messages/models.py
pinax/messages/signals.py
pinax/messages/urls.py
pinax/messages/utils.py
pinax/messages/views.py
pinax/messages/migrations/0001_initial.py
pinax/messages/migrations/__init__.py
pinax/messages/templatetags/__init__.py
pinax/messages/templatetags/pinax_messages_tags.py
pinax/messages/tests/__init__.py
pinax/messages/tests/models.py
pinax/messages/tests/test.py
pinax/messages/tests/tests.py
pinax/messages/tests/urls.py
pinax_messages-3.0.0.dist-info/AUTHORS
pinax_messages-3.0.0.dist-info/LICENSE
pinax_messages-3.0.0.dist-info/METADATA
pinax_messages-3.0.0.dist-info/WHEEL
pinax_messages-3.0.0.dist-info/top_level.txt
pinax_messages-3.0.0.dist-info/RECORD
